matrice_streaming/__init__.py
matrice_streaming/py.typed
matrice_streaming/client/__init__.py
matrice_streaming/client/client.py
matrice_streaming/client/client_utils.py
matrice_streaming/deployment/__init__.py
matrice_streaming/deployment/camera_manager.py
matrice_streaming/deployment/deployment.py
matrice_streaming/deployment/inference_pipeline.py
matrice_streaming/deployment/streaming_gateway_manager.py
matrice_streaming/deployment/todo.txt
matrice_streaming/streaming_gateway/__init__.py
matrice_streaming/streaming_gateway/dynamic_camera_manager.py
matrice_streaming/streaming_gateway/event_listener.py
matrice_streaming/streaming_gateway/metrics_reporter.py
matrice_streaming/streaming_gateway/streaming_action.py
matrice_streaming/streaming_gateway/streaming_gateway.py
matrice_streaming/streaming_gateway/streaming_gateway_utils.py
matrice_streaming/streaming_gateway/streaming_status_listener.py
matrice_streaming/streaming_gateway/camera_streamer/ARCHITECTURE.md
matrice_streaming/streaming_gateway/camera_streamer/__init__.py
matrice_streaming/streaming_gateway/camera_streamer/async_camera_worker.py
matrice_streaming/streaming_gateway/camera_streamer/async_ffmpeg_worker.py
matrice_streaming/streaming_gateway/camera_streamer/camera_streamer.py
matrice_streaming/streaming_gateway/camera_streamer/device_detection.py
matrice_streaming/streaming_gateway/camera_streamer/encoder_manager.py
matrice_streaming/streaming_gateway/camera_streamer/encoding_pool_manager.py
matrice_streaming/streaming_gateway/camera_streamer/ffmpeg_camera_streamer.py
matrice_streaming/streaming_gateway/camera_streamer/ffmpeg_config.py
matrice_streaming/streaming_gateway/camera_streamer/ffmpeg_worker_manager.py
matrice_streaming/streaming_gateway/camera_streamer/frame_processor.py
matrice_streaming/streaming_gateway/camera_streamer/gstreamer_camera_streamer.py
matrice_streaming/streaming_gateway/camera_streamer/gstreamer_worker.py
matrice_streaming-0.1.74.dist-info/licenses/LICENSE.txt
matrice_streaming-0.1.74.dist-info/METADATA
matrice_streaming-0.1.74.dist-info/WHEEL
matrice_streaming-0.1.74.dist-info/top_level.txt
matrice_streaming-0.1.74.dist-info/RECORD
